LICENSE
MANIFEST.in
README.md
requirements.txt
setup.py
aiokafka_rpc/__init__.py
aiokafka_rpc/client.py
aiokafka_rpc/rpc.py
aiokafka_rpc/utils.py
aiokafka_rpc.egg-info/PKG-INFO
aiokafka_rpc.egg-info/SOURCES.txt
aiokafka_rpc.egg-info/dependency_links.txt
aiokafka_rpc.egg-info/requires.txt
aiokafka_rpc.egg-info/top_level.txt