Metadata-Version: 1.1
Name: aiokafka-rpc
Version: 1.3.0
Summary: RPC over Apache Kafka for Python using asyncio
Home-page: https://github.com/fabregas/aiokafka_rpc
Author: Kostiantyn Andrusenko
Author-email: kksstt@gmail.com
License: Apache Software License
Keywords: aiokafka_rpc
Platform: UNKNOWN
Classifier: Development Status :: 5 - Production/Stable
Classifier: Topic :: Software Development :: Libraries
Classifier: License :: OSI Approved :: Apache Software License
Classifier: Programming Language :: Python :: 3
